LICENSE
MANIFEST.in
README.md
setup.py
django_time_logger.egg-info/PKG-INFO
django_time_logger.egg-info/SOURCES.txt
django_time_logger.egg-info/dependency_links.txt
django_time_logger.egg-info/requires.txt
django_time_logger.egg-info/top_level.txt
time_logger/__init__.py
time_logger/forms.py
time_logger/models.py
time_logger/models_mongo.py
time_logger/mysql_logs_parser_from_file.py
time_logger/tests.py
time_logger/urls.py
time_logger/views.py
time_logger/management/__init__.py
time_logger/management/commands/__init__.py
time_logger/management/commands/bin_log_to_mongo.py
time_logger/management/commands/remove_old_logs.py
time_logger/management/commands/slow_logs_from_db.py
time_logger/management/commands/slow_logs_from_file.py
time_logger/middleware/__init__.py
time_logger/middleware/view_logger.py
time_logger/templates/time_logger/bin_log.html
time_logger/templates/time_logger/slow_queries_log.html
time_logger/templates/time_logger/view_log_detail.html
time_logger/templates/time_logger/views_log.html