Metadata-Version: 1.0
Name: django-time-logger
Version: 0.0.17
Summary: Time logger for django
Home-page: https://github.com/telminov/django-time-logger
Author: Telminov Sergey
Author-email: UNKNOWN
License: The MIT License
Platform: UNKNOWN
